Workbook

Sheet Cleaning Service (Lily)
J2: Mushok-6.6
A3: Government of the Peoples Republic of Bangladesh
A4: National Board of Revenue
A5: Withholding Tax Certificate
A6: (See clause (Cha) of Sub- Rule (1) of Rule 40)
A9: Name of withholding entity | D9: : Xpert Fintech Ltd.
A11: Address of withholding entity | D11: : Saiham Sky View Tower, 45, Bijoynagar, Dhaka-1000
A13: BIN of withholding entity (if applicable) | D13: : 004870109-0208
A15: Certificate No: | C15: ='sample VDS_format'!L4 -> e.g. Month_001 | I15: Date of Issue: | J15: ='sample VDS_format'!E4 -> MM/DD/YYYY
A17: This is to certify that VAT has been deducted at source from the supplies having VAT deductible at source in accordance with Section 49 of the Act. The VAT so deducted has been deposited in the government treasury by book transfer/ treasury challan/ increasing adjustment in the return. A copy has been attached (if applicable).
A23: SL NO | B23: Supplier | D23: Treasury Challan | F23: Concerned tax invoice | H23: Total Value of Supply* | I23: Amount of VAT (Taka) | J23: Amount of VAT withheld at source (Taka)
B24: Name | C24: BIN | D24: Number | E24: Date | F24: Number | G24: Date
A25: 1 | B25: ='sample VDS_format'!B4 -> e.g. XYZ Limited | C25: ='sample VDS_format'!C4 -> e.g. 4562367890175 | D25: ='sample VDS_format'!D4 -> e.g. XXXX-0023778273 | E25: ='sample VDS_format'!E4 -> MM/DD/YYYY | F25: ='sample VDS_format'!F4 -> 0 | G25: ='sample VDS_format'!G4 -> 0 | H25: ='sample VDS_format'!H4 -> 11935 | I25: ='sample VDS_format'!I4 -> 1085 | J25: =I31 -> 1085
A26: 2 | J26: is paid through treasury challan no. 2324-0023765273 Dated 14/01/2024 which amounts to BDT 1085.00
A31: Total | H31: =SUM(H25:H30) -> 11935 | I31: =SUM(I25:I30) -> 1085
A34: Officer-in-Charge
A35: Signature
A39: Md. Abdur Rahman Rony ACS
A40: CFO & Company Secrerary
A43: *Price inclusive of VAT and SD (if any).

Sheet Service Charge
J2: Mushok-6.6
A3: Government of the Peoples Republic of Bangladesh
A4: National Board of Revenue
A5: Withholding Tax Certificate
A6: (See clause (Cha) of Sub- Rule (1) of Rule 40)
A9: Name of withholding entity | D9: : Xpert Fintech Ltd.
A11: Address of withholding entity | D11: : Saiham Sky View Tower, 45, Bijoynagar, Dhaka-1000
A13: BIN of withholding entity (if applicable) | D13: : 004870109-0208
A15: Certificate No: | C15: ='sample VDS_format'!#REF! -> #REF! | I15: Date of Issue: | J15: ='sample VDS_format'!#REF! -> #REF!
A17: This is to certify that VAT has been deducted at source from the supplies having VAT deductible at source in accordance with Section 49 of the Act. The VAT so deducted has been deposited in the government treasury by book transfer/ treasury challan/ increasing adjustment in the return. A copy has been attached (if applicable).
A23: SL NO | B23: Supplier | D23: Treasury Challan | F23: Concerned tax invoice | H23: Total Value of Supply* | I23: Amount of VAT (Taka) | J23: Amount of VAT withheld at source (Taka)
B24: Name | C24: BIN | D24: Number | E24: Date | F24: Number | G24: Date
A25: 1 | B25: ='sample VDS_format'!#REF! -> #REF! | C25: ='sample VDS_format'!#REF! -> #REF! | D25: ='sample VDS_format'!#REF! -> #REF! | E25: ='sample VDS_format'!#REF! -> #REF! | F25: ='sample VDS_format'!#REF! -> #REF! | G25: ='sample VDS_format'!#REF! -> #REF! | H25: ='sample VDS_format'!#REF! -> #REF! | I25: ='sample VDS_format'!#REF! -> #REF! | J25: =I31 -> #REF!
A26: 2 | J26: is paid through treasury challan no. 2324-0023834864 Dated 14/01/2024 which amounts to BDT 650.00
A31: Total | H31: =SUM(H25:H30) -> #REF! | I31: =SUM(I25:I30) -> #REF!
A34: Officer-in-Charge
A35: Signature
A39: Md. Abdur Rahman Rony ACS
A40: CFO & Company Secrerary
A43: *Price inclusive of VAT and SD (if any).

Sheet Mohammad Ali
J2: Mushok-6.6
A3: Government of the Peoples Republic of Bangladesh
A4: National Board of Revenue
A5: Withholding Tax Certificate
A6: (See clause (Cha) of Sub- Rule (1) of Rule 40)
A9: Name of withholding entity | D9: : Xpert Fintech Ltd.
A11: Address of withholding entity | D11: : Saiham Sky View Tower, 45, Bijoynagar, Dhaka-1000
A13: BIN of withholding entity (if applicable) | D13: : 004870109-0208
A15: Certificate No: | C15: ='sample VDS_format'!#REF! -> #REF! | I15: Date of Issue: | J15: ='sample VDS_format'!#REF! -> #REF!
A17: This is to certify that VAT has been deducted at source from the supplies having VAT deductible at source in accordance with Section 49 of the Act. The VAT so deducted has been deposited in the government treasury by book transfer/ treasury challan/ increasing adjustment in the return. A copy has been attached (if applicable).
A23: SL NO | B23: Supplier | D23: Treasury Challan | F23: Concerned tax invoice | H23: Total Value of Supply* | I23: Amount of VAT (Taka) | J23: Amount of VAT withheld at source (Taka)
B24: Name | C24: BIN | D24: Number | E24: Date | F24: Number | G24: Date
A25: 1 | B25: ='sample VDS_format'!#REF! -> #REF! | C25: ='sample VDS_format'!#REF! -> #REF! | D25: ='sample VDS_format'!#REF! -> #REF! | E25: ='sample VDS_format'!#REF! -> #REF! | F25: ='sample VDS_format'!#REF! -> #REF! | G25: ='sample VDS_format'!#REF! -> #REF! | H25: ='sample VDS_format'!#REF! -> #REF! | I25: ='sample VDS_format'!#REF! -> #REF! | J25: =SUM(I25:I26) -> #REF!
J26: is paid through treasury challan no. 2324-0023767062 Dated 14/01/2024 which amounts to BDT 30000.00
A31: Total | H31: =SUM(H25:H30) -> #REF! | I31: =SUM(I25:I30) -> #REF!
A34: Officer-in-Charge
A35: Signature
A39: Md. Abdur Rahman Rony ACS
A40: CFO & Company Secrerary
A43: *Price inclusive of VAT and SD (if any).

Sheet Repairing or Servicing-Electra
J2: Mushok-6.6
A3: Government of the Peoples Republic of Bangladesh
A4: National Board of Revenue
A5: Withholding Tax Certificate
A6: (See clause (Cha) of Sub- Rule (1) of Rule 40)
A9: Name of withholding entity | D9: : Xpert Fintech Ltd.
A11: Address of withholding entity | D11: : Saiham Sky View Tower, 45, Bijoynagar, Dhaka-1000
A13: BIN of withholding entity (if applicable) | D13: : 004870109-0208
A15: Certificate No: | C15: ='sample VDS_format'!#REF! -> #REF! | I15: Date of Issue: | J15: ='sample VDS_format'!#REF! -> #REF!
A17: This is to certify that VAT has been deducted at source from the supplies having VAT deductible at source in accordance with Section 49 of the Act. The VAT so deducted has been deposited in the government treasury by book transfer/ treasury challan/ increasing adjustment in the return. A copy has been attached (if applicable).
A23: SL NO | B23: Supplier | D23: Treasury Challan | F23: Concerned tax invoice | H23: Total Value of Supply* | I23: Amount of VAT (Taka) | J23: Amount of VAT withheld at source (Taka)
B24: Name | C24: BIN | D24: Number | E24: Date | F24: Number | G24: Date
A25: 1 | B25: ='sample VDS_format'!#REF! -> #REF! | C25: ='sample VDS_format'!#REF! -> #REF! | D25: ='sample VDS_format'!#REF! -> #REF! | E25: ='sample VDS_format'!#REF! -> #REF! | F25: ='sample VDS_format'!#REF! -> #REF! | G25: ='sample VDS_format'!#REF! -> #REF! | H25: ='sample VDS_format'!#REF! -> #REF! | I25: ='sample VDS_format'!#REF! -> #REF! | J25: =SUM(I25:I26) -> #REF!
J26: is paid through treasury challan no. 2324-0023767340 Dated 14/01/2024 which amounts to BDT 60.00
A31: Total | H31: =SUM(H25:H30) -> #REF! | I31: =SUM(I25:I30) -> #REF!
A34: Officer-in-Charge
A35: Signature
A39: Md. Abdur Rahman Rony ACS
A40: CFO & Company Secrerary
A43: *Price inclusive of VAT and SD (if any).

Sheet Cleaning Service (Anika)
J2: Mushok-6.6
A3: Government of the Peoples Republic of Bangladesh
A4: National Board of Revenue
A5: Withholding Tax Certificate
A6: (See clause (Cha) of Sub- Rule (1) of Rule 40)
A9: Name of withholding entity | D9: : Xpert Fintech Ltd.
A11: Address of withholding entity | D11: : Saiham Sky View Tower, 45, Bijoynagar, Dhaka-1000
A13: BIN of withholding entity (if applicable) | D13: : 004870109-0208
A15: Certificate No: | C15: ='sample VDS_format'!#REF! -> #REF! | I15: Date of Issue: | J15: ='sample VDS_format'!#REF! -> #REF!
A17: This is to certify that VAT has been deducted at source from the supplies having VAT deductible at source in accordance with Section 49 of the Act. The VAT so deducted has been deposited in the government treasury by book transfer/ treasury challan/ increasing adjustment in the return. A copy has been attached (if applicable).
A23: SL NO | B23: Supplier | D23: Treasury Challan | F23: Concerned tax invoice | H23: Total Value of Supply* | I23: Amount of VAT (Taka) | J23: Amount of VAT withheld at source (Taka)
B24: Name | C24: BIN | D24: Number | E24: Date | F24: Number | G24: Date
A25: 1 | B25: ='sample VDS_format'!#REF! -> #REF! | C25: ='sample VDS_format'!#REF! -> #REF! | D25: ='sample VDS_format'!#REF! -> #REF! | E25: ='sample VDS_format'!#REF! -> #REF! | F25: ='sample VDS_format'!#REF! -> #REF! | G25: ='sample VDS_format'!#REF! -> #REF! | H25: ='sample VDS_format'!#REF! -> #REF! | I25: ='sample VDS_format'!#REF! -> #REF! | J25: =I31 -> #REF!
A26: 2 | J26: is paid through treasury challan no. 2324-0019980322 Dated 10/12/2023 which amounts to BDT 475.00
A27: 3
A31: Total | H31: =SUM(H25:H30) -> #REF! | I31: =SUM(I25:I30) -> #REF!
A34: Officer-in-Charge
A35: Signature
A39: Md. Abdur Rahman Rony ACS
A40: CFO & Company Secrerary
A43: *Price inclusive of VAT and SD (if any).

Sheet BRACNet
J2: Mushok-6.6
A3: Government of the Peoples Republic of Bangladesh
A4: National Board of Revenue
A5: Withholding Tax Certificate
A6: (See clause (Cha) of Sub- Rule (1) of Rule 40)
A9: Name of withholding entity | D9: : Xpert Fintech Ltd.
A11: Address of withholding entity | D11: : Saiham Sky View Tower, 45, Bijoynagar, Dhaka-1000
A13: BIN of withholding entity (if applicable) | D13: : 004870109-0208
A15: Certificate No: | C15: ='sample VDS_format'!#REF! -> #REF! | I15: Date of Issue: | J15: ='sample VDS_format'!#REF! -> #REF!
A17: This is to certify that VAT has been deducted at source from the supplies having VAT deductible at source in accordance with Section 49 of the Act. The VAT so deducted has been deposited in the government treasury by book transfer/ treasury challan/ increasing adjustment in the return. A copy has been attached (if applicable).
A23: SL NO | B23: Supplier | D23: Treasury Challan | F23: Concerned tax invoice | H23: Total Value of Supply* | I23: Amount of VAT (Taka) | J23: Amount of VAT withheld at source (Taka)
B24: Name | C24: BIN | D24: Number | E24: Date | F24: Number | G24: Date
A25: 1 | B25: ='sample VDS_format'!#REF! -> #REF! | C25: ='sample VDS_format'!#REF! -> #REF! | D25: ='sample VDS_format'!#REF! -> #REF! | E25: ='sample VDS_format'!#REF! -> #REF! | H25: ='sample VDS_format'!#REF! -> #REF! | I25: ='sample VDS_format'!#REF! -> #REF! | J25: =SUM(I25:I26) -> #REF!
J26: is paid through treasury challan no. 2324-0019985624 Dated 10/12/2023 which amounts to BDT 653.10
A31: Total | H31: =SUM(H25:H30) -> #REF! | I31: =SUM(I25:I30) -> #REF!
A34: Officer-in-Charge
A35: Signature
A39: Md. Abdur Rahman Rony ACS
A40: CFO & Company Secrerary
A43: *Price inclusive of VAT and SD (if any).

Sheet Computer Expense
J2: Mushok-6.6
A3: Government of the Peoples Republic of Bangladesh
A4: National Board of Revenue
A5: Withholding Tax Certificate
A6: (See clause (Cha) of Sub- Rule (1) of Rule 40)
A9: Name of withholding entity | D9: : Xpert Fintech Ltd.
A11: Address of withholding entity | D11: : Saiham Sky View Tower, 45, Bijoynagar, Dhaka-1000
A13: BIN of withholding entity (if applicable) | D13: : 004870109-0208
A15: Certificate No: | C15: ='sample VDS_format'!#REF! -> #REF! | I15: Date of Issue: | J15: ='sample VDS_format'!#REF! -> #REF!
A17: This is to certify that VAT has been deducted at source from the supplies having VAT deductible at source in accordance with Section 49 of the Act. The VAT so deducted has been deposited in the government treasury by book transfer/ treasury challan/ increasing adjustment in the return. A copy has been attached (if applicable).
A23: SL NO | B23: Supplier | D23: Treasury Challan | F23: Concerned tax invoice | H23: Total Value of Supply* | I23: Amount of VAT (Taka) | J23: Amount of VAT withheld at source (Taka)
B24: Name | C24: BIN | D24: Number | E24: Date | F24: Number | G24: Date
A25: 1 | B25: ='sample VDS_format'!#REF! -> #REF! | C25: ='sample VDS_format'!#REF! -> #REF! | D25: ='sample VDS_format'!#REF! -> #REF! | E25: ='sample VDS_format'!#REF! -> #REF! | H25: ='sample VDS_format'!#REF! -> #REF! | I25: ='sample VDS_format'!#REF! -> #REF! | J25: =SUM(I25:I26) -> #REF!
J26: is paid through treasury challan no. 2324-0019986308 Dated 10/12/2023 which amounts to BDT 48.75
A31: Total | H31: =SUM(H25:H30) -> #REF! | I31: =SUM(I25:I30) -> #REF!
A34: Officer-in-Charge
A35: Signature
A39: Md. Abdur Rahman Rony ACS
A40: CFO & Company Secrerary
A43: *Price inclusive of VAT and SD (if any).

Sheet BD Graph
J2: Mushok-6.6
A3: Government of the Peoples Republic of Bangladesh
A4: National Board of Revenue
A5: Withholding Tax Certificate
A6: (See clause (Cha) of Sub- Rule (1) of Rule 40)
A9: Name of withholding entity | D9: : Xpert Fintech Ltd.
A11: Address of withholding entity | D11: : Saiham Sky View Tower, 45, Bijoynagar, Dhaka-1000
A13: BIN of withholding entity (if applicable) | D13: : 004870109-0208
A15: Certificate No: | C15: ='sample VDS_format'!#REF! -> #REF! | I15: Date of Issue: | J15: ='sample VDS_format'!#REF! -> #REF!
A17: This is to certify that VAT has been deducted at source from the supplies having VAT deductible at source in accordance with Section 49 of the Act. The VAT so deducted has been deposited in the government treasury by book transfer/ treasury challan/ increasing adjustment in the return. A copy has been attached (if applicable).
A23: SL NO | B23: Supplier | D23: Treasury Challan | F23: Concerned tax invoice | H23: Total Value of Supply* | I23: Amount of VAT (Taka) | J23: Amount of VAT withheld at source (Taka)
B24: Name | C24: BIN | D24: Number | E24: Date | F24: Number | G24: Date
A25: 1 | B25: ='sample VDS_format'!#REF! -> #REF! | C25: ='sample VDS_format'!#REF! -> #REF! | D25: ='sample VDS_format'!#REF! -> #REF! | E25: ='sample VDS_format'!#REF! -> #REF! | F25: ='sample VDS_format'!#REF! -> #REF! | G25: ='sample VDS_format'!#REF! -> #REF! | H25: ='sample VDS_format'!#REF! -> #REF! | I25: ='sample VDS_format'!#REF! -> #REF! | J25: =SUM(I25:I26) -> #REF!
J26: is paid through treasury challan no. 2324-0016535736 Dated 13/11/2023 which amounts to BDT 337.50
A31: Total | H31: =SUM(H25:H30) -> #REF! | I31: =SUM(I25:I30) -> #REF!
A34: Officer-in-Charge
A35: Signature
A39: Md. Abdur Rahman Rony ACS
A40: CFO & Company Secrerary
A43: *Price inclusive of VAT and SD (if any).

Sheet sample VDS_format
A2: Sub Form for Note 24 (VAT Deducted at Source from Suppliers)
A3: SL | B3: Supplier's Name | C3: Supplier's BIN | D3: Tax Deposit Serial No.of Bank transfer | E3: Tax Deposit Date | F3: Concerned Invoiced number | G3: Invoice/Challan/Bill date | H3: Value (Including VAT) | I3: Deducted VAT | J3: Value (Excluding VAT) | K3: VAT Rate | L3: Mushak-6.6 Number | M3: Notes
A4: 1 | B4: e.g. XYZ Limited | C4: e.g. 4562367890175 | D4: e.g. XXXX-0023778273 | E4: MM/DD/YYYY | H4: =J4+I4 -> 11935 | I4: 1085 | J4: =I4/K4 -> 10850 | K4: 0.1 | L4: e.g. Month_001 | M4: e.g. mention the service
